anichk.py
AniChk-1.0.0.dist-info/LICENSE
AniChk-1.0.0.dist-info/METADATA
AniChk-1.0.0.dist-info/WHEEL
AniChk-1.0.0.dist-info/entry_points.txt
AniChk-1.0.0.dist-info/top_level.txt
AniChk-1.0.0.dist-info/RECORD
