Metadata-Version: 2.2
Name: AniChk
Version: 1.0.0
Summary: A tool to generate phrases based on file or directory checksum
Home-page: https://github.com/nixietab/anichk
Author: Nixietab
Classifier: Programming Language :: Python :: 3
Classifier: License :: OSI Approved :: MIT License
Classifier: Operating System :: OS Independent
Requires-Python: >=3.6
License-File: LICENSE
Dynamic: author
Dynamic: classifier
Dynamic: home-page
Dynamic: requires-python
Dynamic: summary
